odoo/addons/sm_collaborators/__init__.py
odoo/addons/sm_collaborators/__manifest__.py
odoo/addons/sm_collaborators/models/__init__.py
odoo/addons/sm_collaborators/models/models_sm_collaborator.py
odoo/addons/sm_collaborators/models/models_sm_collaborator_fetch_wizard.py
odoo/addons/sm_collaborators/security/ir.model.access.csv
odoo/addons/sm_collaborators/views/views.xml
odoo/addons/sm_collaborators/views/views_collaborator.xml
odoo/addons/sm_collaborators/views/views_collaborator_actions.xml
odoo/addons/sm_collaborators/views/views_collaborator_fetch_wizard.xml
odoo11_addon_sm_collaborators-11.0.0.0.3.dist-info/METADATA
odoo11_addon_sm_collaborators-11.0.0.0.3.dist-info/WHEEL
odoo11_addon_sm_collaborators-11.0.0.0.3.dist-info/top_level.txt
odoo11_addon_sm_collaborators-11.0.0.0.3.dist-info/RECORD
